elasticsearch_kibana_cli/ElasticsearchKibanaCLI.py
elasticsearch_kibana_cli/ElasticsearchKibanaInterface.py
elasticsearch_kibana_cli/__init__.py
elasticsearch_kibana_cli/cli/__init__.py
elasticsearch_kibana_cli/cli/click_cli.py
elasticsearch_kibana_cli/cli/entrypoints.py
elasticsearch_kibana_cli/exceptions/ElasticsearchKibanaCLIException.py
elasticsearch_kibana_cli/exceptions/__init__.py
elasticsearch_kibana_cli/utils/__init__.py
elasticsearch_kibana_cli/utils/config.py
elasticsearch_kibana_cli/utils/connection.py
elasticsearch_kibana_cli/utils/internal_proxy.py
elasticsearch_kibana_cli/utils/logger.py
elasticsearch_kibana_cli/utils/output.py
elasticsearch_kibana_cli/utils/search.py
elasticsearch_kibana_cli/utils/summary.py
elasticsearch_kibana_cli-0.6.1.dist-info/LICENSE
elasticsearch_kibana_cli-0.6.1.dist-info/METADATA
elasticsearch_kibana_cli-0.6.1.dist-info/WHEEL
elasticsearch_kibana_cli-0.6.1.dist-info/entry_points.txt
elasticsearch_kibana_cli-0.6.1.dist-info/top_level.txt
elasticsearch_kibana_cli-0.6.1.dist-info/zip-safe
elasticsearch_kibana_cli-0.6.1.dist-info/RECORD
