Metadata-Version: 2.1
Name: elasticsearch-kibana-cli
Version: 0.6.1
Summary: CLI interface to query Elasticsearch backend via the Kibana frontend.
Home-page: https://github.com/ndejong/elasticsearch_kibana_cli
Author: Nicholas de Jong
Author-email: contact@nicholasdejong.com
License: BSD2
Keywords: kibana,elasticsearch,elasticsearch-client
Platform: UNKNOWN
Classifier: Intended Audience :: System Administrators
Classifier: Intended Audience :: Information Technology
Classifier: Programming Language :: Python :: 3.6
Classifier: Programming Language :: Python :: 3.7
Classifier: Programming Language :: Python :: 3.8
Classifier: Programming Language :: Python :: 3.9
Classifier: License :: OSI Approved :: BSD License
Requires-Python: >=3.6.0,<4.0.0
License-File: LICENSE
Requires-Dist: click
Requires-Dist: bs4
Requires-Dist: maya
Requires-Dist: dpath
Requires-Dist: Flask
Requires-Dist: PyYAML
Requires-Dist: urllib3
Requires-Dist: chardet
Requires-Dist: requests
Requires-Dist: elasticsearch-dsl
